{
  "data": {
    "items": [
      {
        "created": 1692651716506340000,
        "createdFormatted": "۳۰ مرداد ۱۴۰۲",
        "name": "رضوانشهر",
        "province": {
          "countryId": "ir",
          "created": 1692651714579138000,
          "name": "یزد",
          "uniqueId": "iran_yazd",
          "updated": 1692651714579138000,
          "userId": "",
          "visibility": "A",
          "workspaceId": ""
        },
        "provinceId": "iran_yazd",
        "uniqueId": "iran_city_1160",
        "updated": 1692651716506340000,
        "userId": "",
        "workspaceId": ""
      },
      {
        "created": 1692651716504331000,
        "createdFormatted": "۳۰ مرداد ۱۴۰۲",
        "name": "پیربازار",
        "province": {
          "countryId": "ir",
          "created": 1692651714571196000,
          "name": "گیلان",
          "uniqueId": "iran_gilan",
          "updated": 1692651714571196000,
          "userId": "",
          "visibility": "A",
          "workspaceId": ""
        },
        "provinceId": "iran_gilan",
        "uniqueId": "iran_city_1159",
        "updated": 1692651716504331000,
        "userId": "",
        "workspaceId": ""
      },
      {
        "created": 1692651716502642000,
        "createdFormatted": "۳۰ مرداد ۱۴۰۲",
        "name": "بینالود",
        "province": {
          "countryId": "ir",
          "created": 1692651714546899000,
          "name": "خراسان رضوی",
          "uniqueId": "iran_khorasan_razavi",
          "updated": 1692651714546899000,
          "userId": "",
          "visibility": "A",
          "workspaceId": ""
        },
        "provinceId": "iran_khorasan_razavi",
        "uniqueId": "iran_city_1155",
        "updated": 1692651716502642000,
        "userId": "",
        "workspaceId": ""
      },
      {
        "created": 1692651716501157000,
        "createdFormatted": "۳۰ مرداد ۱۴۰۲",
        "name": "قیامدشت",
        "province": {
          "countryId": "ir",
          "created": 1692651714541867000,
          "name": "تهران",
          "uniqueId": "iran_tehran",
          "updated": 1692651714541867000,
          "userId": "",
          "visibility": "A",
          "workspaceId": ""
        },
        "provinceId": "iran_tehran",
        "uniqueId": "iran_city_1153",
        "updated": 1692651716501157000,
        "userId": "",
        "workspaceId": ""
      },
      {
        "created": 1692651716499802000,
        "createdFormatted": "۳۰ مرداد ۱۴۰۲",
        "name": "گلبهار",
        "province": {
          "countryId": "ir",
          "created": 1692651714546899000,
          "name": "خراسان رضوی",
          "uniqueId": "iran_khorasan_razavi",
          "updated": 1692651714546899000,
          "userId": "",
          "visibility": "A",
          "workspaceId": ""
        },
        "provinceId": "iran_khorasan_razavi",
        "uniqueId": "iran_city_1150",
        "updated": 1692651716499802000,
        "userId": "",
        "workspaceId": ""
      },
      {
        "created": 1692651716498486000,
        "createdFormatted": "۳۰ مرداد ۱۴۰۲",
        "name": "تهران دشت",
        "province": {
          "countryId": "ir",
          "created": 1692651714537019000,
          "name": "البرز",
          "uniqueId": "iran_alborz",
          "updated": 1692651714537019000,
          "userId": "",
          "visibility": "A",
          "workspaceId": ""
        },
        "provinceId": "iran_alborz",
        "uniqueId": "iran_city_1138",
        "updated": 1692651716498486000,
        "userId": "",
        "workspaceId": ""
      },
      {
        "created": 1692651716497140000,
        "createdFormatted": "۳۰ مرداد ۱۴۰۲",
        "name": "ساوجبلاغ",
        "province": {
          "countryId": "ir",
          "created": 1692651714537019000,
          "name": "البرز",
          "uniqueId": "iran_alborz",
          "updated": 1692651714537019000,
          "userId": "",
          "visibility": "A",
          "workspaceId": ""
        },
        "provinceId": "iran_alborz",
        "uniqueId": "iran_city_1137",
        "updated": 1692651716497140000,
        "userId": "",
        "workspaceId": ""
      },
      {
        "created": 1692651716495780000,
        "createdFormatted": "۳۰ مرداد ۱۴۰۲",
        "name": "کردان",
        "province": {
          "countryId": "ir",
          "created": 1692651714537019000,
          "name": "البرز",
          "uniqueId": "iran_alborz",
          "updated": 1692651714537019000,
          "userId": "",
          "visibility": "A",
          "workspaceId": ""
        },
        "provinceId": "iran_alborz",
        "uniqueId": "iran_city_1135",
        "updated": 1692651716495780000,
        "userId": "",
        "workspaceId": ""
      },
      {
        "created": 1692651716494352000,
        "createdFormatted": "۳۰ مرداد ۱۴۰۲",
        "name": "زیباکنار",
        "province": {
          "countryId": "ir",
          "created": 1692651714571196000,
          "name": "گیلان",
          "uniqueId": "iran_gilan",
          "updated": 1692651714571196000,
          "userId": "",
          "visibility": "A",
          "workspaceId": ""
        },
        "provinceId": "iran_gilan",
        "uniqueId": "iran_city_1121",
        "updated": 1692651716494352000,
        "userId": "",
        "workspaceId": ""
      },
      {
        "created": 1692651716492939000,
        "createdFormatted": "۳۰ مرداد ۱۴۰۲",
        "name": "سادات شهر",
        "province": {
          "countryId": "ir",
          "created": 1692651714572781000,
          "name": "مازندران",
          "uniqueId": "iran_mazandaran",
          "updated": 1692651714572781000,
          "userId": "",
          "visibility": "A",
          "workspaceId": ""
        },
        "provinceId": "iran_mazandaran",
        "uniqueId": "iran_city_1119",
        "updated": 1692651716492939000,
        "userId": "",
        "workspaceId": ""
      },
      {
        "created": 1692651716491525000,
        "createdFormatted": "۳۰ مرداد ۱۴۰۲",
        "name": "مارلیک",
        "province": {
          "countryId": "ir",
          "created": 1692651714537019000,
          "name": "البرز",
          "uniqueId": "iran_alborz",
          "updated": 1692651714537019000,
          "userId": "",
          "visibility": "A",
          "workspaceId": ""
        },
        "provinceId": "iran_alborz",
        "uniqueId": "iran_city_1118",
        "updated": 1692651716491525000,
        "userId": "",
        "workspaceId": ""
      },
      {
        "created": 1692651716490172000,
        "createdFormatted": "۳۰ مرداد ۱۴۰۲",
        "name": "فردیس",
        "province": {
          "countryId": "ir",
          "created": 1692651714537019000,
          "name": "البرز",
          "uniqueId": "iran_alborz",
          "updated": 1692651714537019000,
          "userId": "",
          "visibility": "A",
          "workspaceId": ""
        },
        "provinceId": "iran_alborz",
        "uniqueId": "iran_city_1117",
        "updated": 1692651716490172000,
        "userId": "",
        "workspaceId": ""
      },
      {
        "created": 1692651716488843000,
        "createdFormatted": "۳۰ مرداد ۱۴۰۲",
        "name": "پرند",
        "province": {
          "countryId": "ir",
          "created": 1692651714541867000,
          "name": "تهران",
          "uniqueId": "iran_tehran",
          "updated": 1692651714541867000,
          "userId": "",
          "visibility": "A",
          "workspaceId": ""
        },
        "provinceId": "iran_tehran",
        "uniqueId": "iran_city_1116",
        "updated": 1692651716488843000,
        "userId": "",
        "workspaceId": ""
      },
      {
        "created": 1692651716487465000,
        "createdFormatted": "۳۰ مرداد ۱۴۰۲",
        "name": "یزد",
        "province": {
          "countryId": "ir",
          "created": 1692651714579138000,
          "name": "یزد",
          "uniqueId": "iran_yazd",
          "updated": 1692651714579138000,
          "userId": "",
          "visibility": "A",
          "workspaceId": ""
        },
        "provinceId": "iran_yazd",
        "uniqueId": "iran_city_1111",
        "updated": 1692651716487465000,
        "userId": "",
        "workspaceId": ""
      },
      {
        "created": 1692651716486128000,
        "createdFormatted": "۳۰ مرداد ۱۴۰۲",
        "name": "هرات",
        "province": {
          "countryId": "ir",
          "created": 1692651714579138000,
          "name": "یزد",
          "uniqueId": "iran_yazd",
          "updated": 1692651714579138000,
          "userId": "",
          "visibility": "A",
          "workspaceId": ""
        },
        "provinceId": "iran_yazd",
        "uniqueId": "iran_city_1110",
        "updated": 1692651716486128000,
        "userId": "",
        "workspaceId": ""
      },
      {
        "created": 1692651716484486000,
        "createdFormatted": "۳۰ مرداد ۱۴۰۲",
        "name": "نیر",
        "province": {
          "countryId": "ir",
          "created": 1692651714579138000,
          "name": "یزد",
          "uniqueId": "iran_yazd",
          "updated": 1692651714579138000,
          "userId": "",
          "visibility": "A",
          "workspaceId": ""
        },
        "provinceId": "iran_yazd",
        "uniqueId": "iran_city_1109",
        "updated": 1692651716484486000,
        "userId": "",
        "workspaceId": ""
      },
      {
        "created": 1692651716483174000,
        "createdFormatted": "۳۰ مرداد ۱۴۰۲",
        "name": "ندوشن",
        "province": {
          "countryId": "ir",
          "created": 1692651714579138000,
          "name": "یزد",
          "uniqueId": "iran_yazd",
          "updated": 1692651714579138000,
          "userId": "",
          "visibility": "A",
          "workspaceId": ""
        },
        "provinceId": "iran_yazd",
        "uniqueId": "iran_city_1108",
        "updated": 1692651716483174000,
        "userId": "",
        "workspaceId": ""
      },
      {
        "created": 1692651716481854000,
        "createdFormatted": "۳۰ مرداد ۱۴۰۲",
        "name": "میبد",
        "province": {
          "countryId": "ir",
          "created": 1692651714579138000,
          "name": "یزد",
          "uniqueId": "iran_yazd",
          "updated": 1692651714579138000,
          "userId": "",
          "visibility": "A",
          "workspaceId": ""
        },
        "provinceId": "iran_yazd",
        "uniqueId": "iran_city_1107",
        "updated": 1692651716481854000,
        "userId": "",
        "workspaceId": ""
      },
      {
        "created": 1692651716480513000,
        "createdFormatted": "۳۰ مرداد ۱۴۰۲",
        "name": "مهریز",
        "province": {
          "countryId": "ir",
          "created": 1692651714579138000,
          "name": "یزد",
          "uniqueId": "iran_yazd",
          "updated": 1692651714579138000,
          "userId": "",
          "visibility": "A",
          "workspaceId": ""
        },
        "provinceId": "iran_yazd",
        "uniqueId": "iran_city_1106",
        "updated": 1692651716480513000,
        "userId": "",
        "workspaceId": ""
      },
      {
        "created": 1692651716479114000,
        "createdFormatted": "۳۰ مرداد ۱۴۰۲",
        "name": "مهردشت",
        "province": {
          "countryId": "ir",
          "created": 1692651714579138000,
          "name": "یزد",
          "uniqueId": "iran_yazd",
          "updated": 1692651714579138000,
          "userId": "",
          "visibility": "A",
          "workspaceId": ""
        },
        "provinceId": "iran_yazd",
        "uniqueId": "iran_city_1105",
        "updated": 1692651716479114000,
        "userId": "",
        "workspaceId": ""
      },
      {
        "created": 1692651716477679000,
        "createdFormatted": "۳۰ مرداد ۱۴۰۲",
        "name": "مروست",
        "province": {
          "countryId": "ir",
          "created": 1692651714579138000,
          "name": "یزد",
          "uniqueId": "iran_yazd",
          "updated": 1692651714579138000,
          "userId": "",
          "visibility": "A",
          "workspaceId": ""
        },
        "provinceId": "iran_yazd",
        "uniqueId": "iran_city_1104",
        "updated": 1692651716477679000,
        "userId": "",
        "workspaceId": ""
      },
      {
        "created": 1692651716476239000,
        "createdFormatted": "۳۰ مرداد ۱۴۰۲",
        "name": "عقدا",
        "province": {
          "countryId": "ir",
          "created": 1692651714579138000,
          "name": "یزد",
          "uniqueId": "iran_yazd",
          "updated": 1692651714579138000,
          "userId": "",
          "visibility": "A",
          "workspaceId": ""
        },
        "provinceId": "iran_yazd",
        "uniqueId": "iran_city_1103",
        "updated": 1692651716476239000,
        "userId": "",
        "workspaceId": ""
      },
      {
        "created": 1692651716474815000,
        "createdFormatted": "۳۰ مرداد ۱۴۰۲",
        "name": "طبس",
        "province": {
          "countryId": "ir",
          "created": 1692651714579138000,
          "name": "یزد",
          "uniqueId": "iran_yazd",
          "updated": 1692651714579138000,
          "userId": "",
          "visibility": "A",
          "workspaceId": ""
        },
        "provinceId": "iran_yazd",
        "uniqueId": "iran_city_1101",
        "updated": 1692651716474815000,
        "userId": "",
        "workspaceId": ""
      },
      {
        "created": 1692651716473350000,
        "createdFormatted": "۳۰ مرداد ۱۴۰۲",
        "name": "شاهدیه",
        "province": {
          "countryId": "ir",
          "created": 1692651714579138000,
          "name": "یزد",
          "uniqueId": "iran_yazd",
          "updated": 1692651714579138000,
          "userId": "",
          "visibility": "A",
          "workspaceId": ""
        },
        "provinceId": "iran_yazd",
        "uniqueId": "iran_city_1100",
        "updated": 1692651716473350000,
        "userId": "",
        "workspaceId": ""
      },
      {
        "created": 1692651716471897000,
        "createdFormatted": "۳۰ مرداد ۱۴۰۲",
        "name": "زارچ",
        "province": {
          "countryId": "ir",
          "created": 1692651714579138000,
          "name": "یزد",
          "uniqueId": "iran_yazd",
          "updated": 1692651714579138000,
          "userId": "",
          "visibility": "A",
          "workspaceId": ""
        },
        "provinceId": "iran_yazd",
        "uniqueId": "iran_city_1099",
        "updated": 1692651716471897000,
        "userId": "",
        "workspaceId": ""
      },
      {
        "created": 1692651716470328000,
        "createdFormatted": "۳۰ مرداد ۱۴۰۲",
        "name": "دیهوک",
        "province": {
          "countryId": "ir",
          "created": 1692651714579138000,
          "name": "یزد",
          "uniqueId": "iran_yazd",
          "updated": 1692651714579138000,
          "userId": "",
          "visibility": "A",
          "workspaceId": ""
        },
        "provinceId": "iran_yazd",
        "uniqueId": "iran_city_1098",
        "updated": 1692651716470328000,
        "userId": "",
        "workspaceId": ""
      },
      {
        "created": 1692651716467994000,
        "createdFormatted": "۳۰ مرداد ۱۴۰۲",
        "name": "خضرآباد",
        "province": {
          "countryId": "ir",
          "created": 1692651714579138000,
          "name": "یزد",
          "uniqueId": "iran_yazd",
          "updated": 1692651714579138000,
          "userId": "",
          "visibility": "A",
          "workspaceId": ""
        },
        "provinceId": "iran_yazd",
        "uniqueId": "iran_city_1097",
        "updated": 1692651716467994000,
        "userId": "",
        "workspaceId": ""
      },
      {
        "created": 1692651716466461000,
        "createdFormatted": "۳۰ مرداد ۱۴۰۲",
        "name": "حمیدیا",
        "province": {
          "countryId": "ir",
          "created": 1692651714579138000,
          "name": "یزد",
          "uniqueId": "iran_yazd",
          "updated": 1692651714579138000,
          "userId": "",
          "visibility": "A",
          "workspaceId": ""
        },
        "provinceId": "iran_yazd",
        "uniqueId": "iran_city_1096",
        "updated": 1692651716466461000,
        "userId": "",
        "workspaceId": ""
      },
      {
        "created": 1692651716464807000,
        "createdFormatted": "۳۰ مرداد ۱۴۰۲",
        "name": "تفت",
        "province": {
          "countryId": "ir",
          "created": 1692651714579138000,
          "name": "یزد",
          "uniqueId": "iran_yazd",
          "updated": 1692651714579138000,
          "userId": "",
          "visibility": "A",
          "workspaceId": ""
        },
        "provinceId": "iran_yazd",
        "uniqueId": "iran_city_1095",
        "updated": 1692651716464807000,
        "userId": "",
        "workspaceId": ""
      },
      {
        "created": 1692651716443391000,
        "createdFormatted": "۳۰ مرداد ۱۴۰۲",
        "name": "بهاباد",
        "province": {
          "countryId": "ir",
          "created": 1692651714579138000,
          "name": "یزد",
          "uniqueId": "iran_yazd",
          "updated": 1692651714579138000,
          "userId": "",
          "visibility": "A",
          "workspaceId": ""
        },
        "provinceId": "iran_yazd",
        "uniqueId": "iran_city_1094",
        "updated": 1692651716443391000,
        "userId": "",
        "workspaceId": ""
      },
      {
        "created": 1692651716440565000,
        "createdFormatted": "۳۰ مرداد ۱۴۰۲",
        "name": "بفروئیه",
        "province": {
          "countryId": "ir",
          "created": 1692651714579138000,
          "name": "یزد",
          "uniqueId": "iran_yazd",
          "updated": 1692651714579138000,
          "userId": "",
          "visibility": "A",
          "workspaceId": ""
        },
        "provinceId": "iran_yazd",
        "uniqueId": "iran_city_1093",
        "updated": 1692651716440565000,
        "userId": "",
        "workspaceId": ""
      },
      {
        "created": 1692651716438585000,
        "createdFormatted": "۳۰ مرداد ۱۴۰۲",
        "name": "بافق",
        "province": {
          "countryId": "ir",
          "created": 1692651714579138000,
          "name": "یزد",
          "uniqueId": "iran_yazd",
          "updated": 1692651714579138000,
          "userId": "",
          "visibility": "A",
          "workspaceId": ""
        },
        "provinceId": "iran_yazd",
        "uniqueId": "iran_city_1092",
        "updated": 1692651716438585000,
        "userId": "",
        "workspaceId": ""
      },
      {
        "created": 1692651716437023000,
        "createdFormatted": "۳۰ مرداد ۱۴۰۲",
        "name": "اشکذر",
        "province": {
          "countryId": "ir",
          "created": 1692651714579138000,
          "name": "یزد",
          "uniqueId": "iran_yazd",
          "updated": 1692651714579138000,
          "userId": "",
          "visibility": "A",
          "workspaceId": ""
        },
        "provinceId": "iran_yazd",
        "uniqueId": "iran_city_1091",
        "updated": 1692651716437023000,
        "userId": "",
        "workspaceId": ""
      },
      {
        "created": 1692651716435677000,
        "createdFormatted": "۳۰ مرداد ۱۴۰۲",
        "name": "اردکان",
        "province": {
          "countryId": "ir",
          "created": 1692651714579138000,
          "name": "یزد",
          "uniqueId": "iran_yazd",
          "updated": 1692651714579138000,
          "userId": "",
          "visibility": "A",
          "workspaceId": ""
        },
        "provinceId": "iran_yazd",
        "uniqueId": "iran_city_1090",
        "updated": 1692651716435677000,
        "userId": "",
        "workspaceId": ""
      },
      {
        "created": 1692651716434301000,
        "createdFormatted": "۳۰ مرداد ۱۴۰۲",
        "name": "احمدآباد",
        "province": {
          "countryId": "ir",
          "created": 1692651714579138000,
          "name": "یزد",
          "uniqueId": "iran_yazd",
          "updated": 1692651714579138000,
          "userId": "",
          "visibility": "A",
          "workspaceId": ""
        },
        "provinceId": "iran_yazd",
        "uniqueId": "iran_city_1089",
        "updated": 1692651716434301000,
        "userId": "",
        "workspaceId": ""
      },
      {
        "created": 1692651716432961000,
        "createdFormatted": "۳۰ مرداد ۱۴۰۲",
        "name": "ابرکوه",
        "province": {
          "countryId": "ir",
          "created": 1692651714579138000,
          "name": "یزد",
          "uniqueId": "iran_yazd",
          "updated": 1692651714579138000,
          "userId": "",
          "visibility": "A",
          "workspaceId": ""
        },
        "provinceId": "iran_yazd",
        "uniqueId": "iran_city_1088",
        "updated": 1692651716432961000,
        "userId": "",
        "workspaceId": ""
      },
      {
        "created": 1692651716431581000,
        "createdFormatted": "۳۰ مرداد ۱۴۰۲",
        "name": "همدان",
        "province": {
          "countryId": "ir",
          "created": 1692651714577525000,
          "name": "همدان",
          "uniqueId": "iran_hamedan",
          "updated": 1692651714577525000,
          "userId": "",
          "visibility": "A",
          "workspaceId": ""
        },
        "provinceId": "iran_hamedan",
        "uniqueId": "iran_city_1087",
        "updated": 1692651716431581000,
        "userId": "",
        "workspaceId": ""
      },
      {
        "created": 1692651716430209000,
        "createdFormatted": "۳۰ مرداد ۱۴۰۲",
        "name": "نهاوند",
        "province": {
          "countryId": "ir",
          "created": 1692651714577525000,
          "name": "همدان",
          "uniqueId": "iran_hamedan",
          "updated": 1692651714577525000,
          "userId": "",
          "visibility": "A",
          "workspaceId": ""
        },
        "provinceId": "iran_hamedan",
        "uniqueId": "iran_city_1086",
        "updated": 1692651716430209000,
        "userId": "",
        "workspaceId": ""
      },
      {
        "created": 1692651716428642000,
        "createdFormatted": "۳۰ مرداد ۱۴۰۲",
        "name": "ملایر",
        "province": {
          "countryId": "ir",
          "created": 1692651714577525000,
          "name": "همدان",
          "uniqueId": "iran_hamedan",
          "updated": 1692651714577525000,
          "userId": "",
          "visibility": "A",
          "workspaceId": ""
        },
        "provinceId": "iran_hamedan",
        "uniqueId": "iran_city_1085",
        "updated": 1692651716428642000,
        "userId": "",
        "workspaceId": ""
      },
      {
        "created": 1692651716427245000,
        "createdFormatted": "۳۰ مرداد ۱۴۰۲",
        "name": "مریانج",
        "province": {
          "countryId": "ir",
          "created": 1692651714577525000,
          "name": "همدان",
          "uniqueId": "iran_hamedan",
          "updated": 1692651714577525000,
          "userId": "",
          "visibility": "A",
          "workspaceId": ""
        },
        "provinceId": "iran_hamedan",
        "uniqueId": "iran_city_1084",
        "updated": 1692651716427245000,
        "userId": "",
        "workspaceId": ""
      },
      {
        "created": 1692651716425742000,
        "createdFormatted": "۳۰ مرداد ۱۴۰۲",
        "name": "لالجین",
        "province": {
          "countryId": "ir",
          "created": 1692651714577525000,
          "name": "همدان",
          "uniqueId": "iran_hamedan",
          "updated": 1692651714577525000,
          "userId": "",
          "visibility": "A",
          "workspaceId": ""
        },
        "provinceId": "iran_hamedan",
        "uniqueId": "iran_city_1083",
        "updated": 1692651716425742000,
        "userId": "",
        "workspaceId": ""
      },
      {
        "created": 1692651716424433000,
        "createdFormatted": "۳۰ مرداد ۱۴۰۲",
        "name": "گیان",
        "province": {
          "countryId": "ir",
          "created": 1692651714577525000,
          "name": "همدان",
          "uniqueId": "iran_hamedan",
          "updated": 1692651714577525000,
          "userId": "",
          "visibility": "A",
          "workspaceId": ""
        },
        "provinceId": "iran_hamedan",
        "uniqueId": "iran_city_1082",
        "updated": 1692651716424433000,
        "userId": "",
        "workspaceId": ""
      },
      {
        "created": 1692651716423065000,
        "createdFormatted": "۳۰ مرداد ۱۴۰۲",
        "name": "گل تپه",
        "province": {
          "countryId": "ir",
          "created": 1692651714577525000,
          "name": "همدان",
          "uniqueId": "iran_hamedan",
          "updated": 1692651714577525000,
          "userId": "",
          "visibility": "A",
          "workspaceId": ""
        },
        "provinceId": "iran_hamedan",
        "uniqueId": "iran_city_1081",
        "updated": 1692651716423065000,
        "userId": "",
        "workspaceId": ""
      },
      {
        "created": 1692651716421753000,
        "createdFormatted": "۳۰ مرداد ۱۴۰۲",
        "name": "کبودر آهنگ",
        "province": {
          "countryId": "ir",
          "created": 1692651714577525000,
          "name": "همدان",
          "uniqueId": "iran_hamedan",
          "updated": 1692651714577525000,
          "userId": "",
          "visibility": "A",
          "workspaceId": ""
        },
        "provinceId": "iran_hamedan",
        "uniqueId": "iran_city_1080",
        "updated": 1692651716421753000,
        "userId": "",
        "workspaceId": ""
      },
      {
        "created": 1692651716420401000,
        "createdFormatted": "۳۰ مرداد ۱۴۰۲",
        "name": "قهاوند",
        "province": {
          "countryId": "ir",
          "created": 1692651714577525000,
          "name": "همدان",
          "uniqueId": "iran_hamedan",
          "updated": 1692651714577525000,
          "userId": "",
          "visibility": "A",
          "workspaceId": ""
        },
        "provinceId": "iran_hamedan",
        "uniqueId": "iran_city_1079",
        "updated": 1692651716420401000,
        "userId": "",
        "workspaceId": ""
      },
      {
        "created": 1692651716418867000,
        "createdFormatted": "۳۰ مرداد ۱۴۰۲",
        "name": "قروه درجزین",
        "province": {
          "countryId": "ir",
          "created": 1692651714577525000,
          "name": "همدان",
          "uniqueId": "iran_hamedan",
          "updated": 1692651714577525000,
          "userId": "",
          "visibility": "A",
          "workspaceId": ""
        },
        "provinceId": "iran_hamedan",
        "uniqueId": "iran_city_1078",
        "updated": 1692651716418867000,
        "userId": "",
        "workspaceId": ""
      },
      {
        "created": 1692651716417406000,
        "createdFormatted": "۳۰ مرداد ۱۴۰۲",
        "name": "فیروزان",
        "province": {
          "countryId": "ir",
          "created": 1692651714577525000,
          "name": "همدان",
          "uniqueId": "iran_hamedan",
          "updated": 1692651714577525000,
          "userId": "",
          "visibility": "A",
          "workspaceId": ""
        },
        "provinceId": "iran_hamedan",
        "uniqueId": "iran_city_1077",
        "updated": 1692651716417406000,
        "userId": "",
        "workspaceId": ""
      },
      {
        "created": 1692651716415981000,
        "createdFormatted": "۳۰ مرداد ۱۴۰۲",
        "name": "فرسفج",
        "province": {
          "countryId": "ir",
          "created": 1692651714577525000,
          "name": "همدان",
          "uniqueId": "iran_hamedan",
          "updated": 1692651714577525000,
          "userId": "",
          "visibility": "A",
          "workspaceId": ""
        },
        "provinceId": "iran_hamedan",
        "uniqueId": "iran_city_1076",
        "updated": 1692651716415981000,
        "userId": "",
        "workspaceId": ""
      },
      {
        "created": 1692651716414644000,
        "createdFormatted": "۳۰ مرداد ۱۴۰۲",
        "name": "فامنین",
        "province": {
          "countryId": "ir",
          "created": 1692651714577525000,
          "name": "همدان",
          "uniqueId": "iran_hamedan",
          "updated": 1692651714577525000,
          "userId": "",
          "visibility": "A",
          "workspaceId": ""
        },
        "provinceId": "iran_hamedan",
        "uniqueId": "iran_city_1075",
        "updated": 1692651716414644000,
        "userId": "",
        "workspaceId": ""
      },
      {
        "created": 1692651716413288000,
        "createdFormatted": "۳۰ مرداد ۱۴۰۲",
        "name": "صالح آباد",
        "province": {
          "countryId": "ir",
          "created": 1692651714577525000,
          "name": "همدان",
          "uniqueId": "iran_hamedan",
          "updated": 1692651714577525000,
          "userId": "",
          "visibility": "A",
          "workspaceId": ""
        },
        "provinceId": "iran_hamedan",
        "uniqueId": "iran_city_1074",
        "updated": 1692651716413288000,
        "userId": "",
        "workspaceId": ""
      }
    ],
    "itemsPerPage": 50,
    "startIndex": 0,
    "totalItems": 1119
  }
}