{
  "data": {
    "items": [
      {
        "created": 1692825318961477000,
        "createdFormatted": "2023/08/23 23:15:18",
        "name": "Hard",
        "translations": [
          {
            "languageId": "fa",
            "linkerId": "hard",
            "name": "سخت"
          },
          {
            "languageId": "en",
            "linkerId": "hard",
            "name": "Hard"
          }
        ],
        "uniqueId": "hard",
        "updated": 1692825318961477000,
        "userId": "",
        "workspaceId": ""
      },
      {
        "created": 1692825318959692000,
        "createdFormatted": "2023/08/23 23:15:18",
        "name": "Medium",
        "translations": [
          {
            "languageId": "fa",
            "linkerId": "medium",
            "name": "متوسط"
          },
          {
            "languageId": "en",
            "linkerId": "medium",
            "name": "Medium"
          }
        ],
        "uniqueId": "medium",
        "updated": 1692825318959692000,
        "userId": "",
        "workspaceId": ""
      },
      {
        "created": 1692825318957716000,
        "createdFormatted": "2023/08/23 23:15:18",
        "name": "Easy",
        "translations": [
          {
            "languageId": "fa",
            "linkerId": "easy",
            "name": "آسان"
          },
          {
            "languageId": "en",
            "linkerId": "easy",
            "name": "Easy"
          }
        ],
        "uniqueId": "easy",
        "updated": 1692825318957716000,
        "userId": "",
        "workspaceId": ""
      }
    ],
    "itemsPerPage": 9999,
    "startIndex": 0,
    "totalItems": 3
  }
}